ringcounter.v
module ringcounter(Q0,Q1,Q2,Q3,Q0comp,Q1comp,Q2comp,Q3comp,clk,rst);

input clk,rst;
output Q0,Q1,Q2,Q3,Q0comp,Q1comp,Q2comp,Q3comp;
wire D0,D1,D2,D3,a,b;

assign a = 1;
assign b = 0;

buf(D0,Q1);
buf(D1,Q2);
buf(D2,Q3);
xor(D3,Q0,Q1);

DFlipFlop DQ0(Q0,Q0comp,D0,clk,rst,a,b);
DFlipFlop DQ1(Q1,Q1comp,D1,clk,rst,b,a);
DFlipFlop DQ2(Q2,Q2comp,D2,clk,rst,b,a);
DFlipFlop DQ3(Q3,Q3comp,D3,clk,rst,a,b);

endmodule

module DFlipFlop(Q,Qcomp,D,clk,rst,a,b);

input D,clk,rst,a,b;
output reg Q,Qcomp;

always @(clk | rst)
begin
   if(rst == 1)
     begin 
       Q = a;
       Qcomp = b;
     end
end

always @(posedge clk)
begin
   Q = D;
   Qcomp = ~Q;
end

endmodule

test_ringcounter.v
module test_ringcounter;

reg clk,rst;
wire Q0,Q0comp,Q1,Q1comp,Q2,Q2comp,Q3,Q3comp;

ringcounter DUT(Q0,Q1,Q2,Q3,Q0comp,Q1comp,Q2comp,Q3comp,clk,rst);

always #10 clk = ~clk;

initial
 begin
  $dumpfile("ringcounter.vcd");
  $dumpvars(0,test_ringcounter);
  $monitor ($time," %b%b%b%b", Q3, Q2, Q1, Q0);
  clk = 0;
  rst = 1;
  #2; rst = 0;
  repeat(20) @(posedge clk);
  $finish;
 end 

endmodule

ringcounter.vcd
$date
	Wed Apr 21 20:09:23 2021
$end
$version
	Icarus Verilog
$end
$timescale
	1s
$end
$scope module test_ringcounter $end
$var wire 1 ! Q3comp $end
$var wire 1 " Q3 $end
$var wire 1 # Q2comp $end
$var wire 1 $ Q2 $end
$var wire 1 % Q1comp $end
$var wire 1 & Q1 $end
$var wire 1 ' Q0comp $end
$var wire 1 ( Q0 $end
$var reg 1 ) clk $end
$var reg 1 * rst $end
$scope module DUT $end
$var wire 1 + D0 $end
$var wire 1 , D1 $end
$var wire 1 - D2 $end
$var wire 1 . D3 $end
$var wire 1 / a $end
$var wire 1 0 b $end
$var wire 1 ) clk $end
$var wire 1 * rst $end
$var wire 1 ! Q3comp $end
$var wire 1 " Q3 $end
$var wire 1 # Q2comp $end
$var wire 1 $ Q2 $end
$var wire 1 % Q1comp $end
$var wire 1 & Q1 $end
$var wire 1 ' Q0comp $end
$var wire 1 ( Q0 $end
$scope module DQ0 $end
$var wire 1 + D $end
$var wire 1 / a $end
$var wire 1 0 b $end
$var wire 1 ) clk $end
$var wire 1 * rst $end
$var reg 1 ( Q $end
$var reg 1 ' Qcomp $end
$upscope $end
$scope module DQ1 $end
$var wire 1 , D $end
$var wire 1 0 a $end
$var wire 1 / b $end
$var wire 1 ) clk $end
$var wire 1 * rst $end
$var reg 1 & Q $end
$var reg 1 % Qcomp $end
$upscope $end
$scope module DQ2 $end
$var wire 1 - D $end
$var wire 1 0 a $end
$var wire 1 / b $end
$var wire 1 ) clk $end
$var wire 1 * rst $end
$var reg 1 $ Q $end
$var reg 1 # Qcomp $end
$upscope $end
$scope module DQ3 $end
$var wire 1 . D $end
$var wire 1 / a $end
$var wire 1 0 b $end
$var wire 1 ) clk $end
$var wire 1 * rst $end
$var reg 1 " Q $end
$var reg 1 ! Qcomp $end
$upscope $end
$upscope $end
$upscope $end
$enddefinitions $end
#0
$dumpvars
00
1/
1.
1-
0,
0+
1*
0)
1(
0'
0&
1%
0$
1#
1"
0!
$end
#2
0*
#10
0.
1,
1'
0(
0#
1$
1)
#20
0)
#30
0-
1.
1+
1!
0"
0%
1&
1)
#40
0)
#50
0.
0,
1-
0'
1(
1#
0$
0!
1"
1)
#60
0)
#70
0-
1,
1.
0+
1!
0"
0#
1$
1%
0&
1)
#80
0)
#90
1+
0,
1-
1'
0(
0%
1&
1#
0$
0!
1"
1)
#100
0)
#110
1,
0+
0#
1$
1%
0&
0'
1(
1)
#120
0)
#130
1+
1'
0(
0%
1&
1)
#140
0)
#150
0.
0'
1(
1)
#160
0)
#170
0-
1!
0"
1)
#180
0)
#190
0,
1#
0$
1)
#200
0)
#210
1.
0+
1%
0&
1)
#220
0)
#230
1-
0.
0!
1"
1'
0(
1)
#240
0)
#250
1,
0-
0#
1$
1!
0"
1)
#260
0)
#270
0,
1.
1+
1#
0$
0%
1&
1)
#280
0)
#290
0+
1-
0'
1(
1%
0&
0!
1"
1)
#300
0)
#310
1,
0.
0#
1$
1'
0(
1)
#320
0)
#330
1.
1+
0-
0%
1&
1!
0"
1)
#340
0)
#350
1-
0,
0.
0!
1"
1#
0$
0'
1(
1)
#360
0)
#370
1.
0+
1,
0-
1%
0&
0#
1$
1!
0"
1)
#380
0)
#390
1-
0,
1+
0!
1"
1#
0$
0%
1&
1'
0(
1)
