graycode.v
module graycode(A,B,C,D,Acomp,Bcomp,Ccomp,Dcomp,clk,rst);

input clk,rst;
output A,B,C,D,Acomp,Bcomp,Ccomp,Dcomp;

wire SA,RA,SB1,SB2,SB3,SB,RB1,RB2,RB3,RB,SC1,SC2,SC,RC1,RC2,RC,SD1,SD2,SD,RD;

and(SA,Bcomp,C,Dcomp);
and(RA,Bcomp,Ccomp,Dcomp);
and(SB1,Acomp,Ccomp,Dcomp);
and(SB2,Acomp,C,D);
and(SB3,A,Ccomp,D);
or(SB,SB1,SB2,SB3);
and(RB1,A,Ccomp,Dcomp);
and(RB2,Acomp,Ccomp,D);
and(RB3,Acomp,C,Dcomp);
or(RB,RB1,RB2,RB3);
and(SC1,Acomp,Bcomp,D);
and(SC2,A,B,D);
or(SC,SC1,SC2);
and(RC1,A,Bcomp,D);
and(RC2,A,B,Dcomp);
or(RC,RC1,RC2);
and(SD1,Acomp,B,Ccomp);
and(SD2,A,Bcomp,C);
or(SD,SD1,SD2);
and(RD,B,C);

SRFlipFlop SRA(A,Acomp,rst,SA,RA,clk);
SRFlipFlop SRB(B,Bcomp,rst,SB,RB,clk);
SRFlipFlop SRC(C,Ccomp,rst,SC,RC,clk);
SRFlipFlop SRD(D,Dcomp,rst,SD,RD,clk);

endmodule

module SRFlipFlop(Q,Qcomp,rst,S,R,clk);

input S,R,rst,clk;
output reg Q,Qcomp;

always @(clk | rst)
begin
  if(rst == 1)
    begin
      Q = 0;
      Qcomp = 1;
    end
end

always @(posedge clk)
begin
   Q = S|(~R&Q);
   Qcomp = ~Q;
end

endmodule

test_SRFlipFlop.v
module test_SRFlipFlop;

reg S,R,clk,rst;
wire Q,Qcomp;

SRFlipFlop DUT(Q,Qcomp,rst,S,R,clk);

always #10 clk = ~clk;

initial
 begin
  $dumpfile("SRFlipFlop.vcd");
  $dumpvars(0,test_SRFlipFlop);
  $monitor ($time,"Q=%b,Qcomp=%b,S=%b,R=%b,clk = %b", Q, Qcomp, S, R, clk);
  clk = 0;
  S= 1; R= 0;
  rst = 1;
  #1; rst = 0;
  #10; S= 0; R= 1; 
  #22; S= 0; R= 0; 
  #26; S= 1; R=0; 
  repeat (2) @(posedge clk);
  $finish;
 end 

endmodule

SRFlipFlop.vcd
$date
	Wed Apr 21 00:32:48 2021
$end
$version
	Icarus Verilog
$end
$timescale
	1s
$end
$scope module test_SRFlipFlop $end
$var wire 1 ! Qcomp $end
$var wire 1 " Q $end
$var reg 1 # R $end
$var reg 1 $ S $end
$var reg 1 % clk $end
$var reg 1 & rst $end
$scope module DUT $end
$var wire 1 # R $end
$var wire 1 $ S $end
$var wire 1 % clk $end
$var wire 1 & rst $end
$var reg 1 " Q $end
$var reg 1 ! Qcomp $end
$upscope $end
$upscope $end
$enddefinitions $end
#0
$dumpvars
1&
0%
1$
0#
x"
x!
$end
#1
0&
#10
0!
1"
1%
#11
1#
0$
#20
0%
#30
1!
0"
1%
#33
0#
#40
0%
#50
1%
#59
1$
#60
0%
#70
0!
1"
1%
